augrs/__init__.py
augrs/__main__.py
augrs/__version__.py
augrs/base.py
augrs/cli.py
augrs/exploit_module.py
augrs/nmap_module.py
augrs/rc_module.py
augrs/tempCodeRunnerFile.py
augrs/validate.py
augrs/modules/__init__.py
augrs/modules/post_exploit_manage.py
augrs-1.0.0.dist-info/LICENSE
augrs-1.0.0.dist-info/METADATA
augrs-1.0.0.dist-info/WHEEL
augrs-1.0.0.dist-info/entry_points.txt
augrs-1.0.0.dist-info/top_level.txt
augrs-1.0.0.dist-info/RECORD
