Metadata-Version: 2.1
Name: augrs
Version: 1.0.0
Summary: An automate metasploit script generator
Author-email: Wisarud Wongta <wisarud2k@gmail.com>
Project-URL: Homepage, https://github.com/Wisarud2k/Autogen_Resource_Script
Classifier: Programming Language :: Python :: 3
Classifier: License :: OSI Approved :: MIT License
Classifier: Operating System :: OS Independent
Requires-Python: >=3.10
License-File: LICENSE
